odoo/addons/purchase_request_substate/README.rst
odoo/addons/purchase_request_substate/__init__.py
odoo/addons/purchase_request_substate/__manifest__.py
odoo/addons/purchase_request_substate/data/purchase_request_substate_data.xml
odoo/addons/purchase_request_substate/data/purchase_substate_mail_template_data.xml
odoo/addons/purchase_request_substate/demo/purchase_request_substate_demo.xml
odoo/addons/purchase_request_substate/i18n/es.po
odoo/addons/purchase_request_substate/i18n/it.po
odoo/addons/purchase_request_substate/i18n/purchase_request_substate.pot
odoo/addons/purchase_request_substate/models/__init__.py
odoo/addons/purchase_request_substate/models/purchase_request.py
odoo/addons/purchase_request_substate/readme/CONTRIBUTORS.rst
odoo/addons/purchase_request_substate/readme/DESCRIPTION.rst
odoo/addons/purchase_request_substate/readme/USAGE.rst
odoo/addons/purchase_request_substate/static/description/icon.png
odoo/addons/purchase_request_substate/static/description/index.html
odoo/addons/purchase_request_substate/tests/__init__.py
odoo/addons/purchase_request_substate/tests/test_purchase_request_substate.py
odoo/addons/purchase_request_substate/views/purchase_request_views.xml
odoo14_addon_purchase_request_substate-14.0.1.0.1.dev8.dist-info/METADATA
odoo14_addon_purchase_request_substate-14.0.1.0.1.dev8.dist-info/WHEEL
odoo14_addon_purchase_request_substate-14.0.1.0.1.dev8.dist-info/top_level.txt
odoo14_addon_purchase_request_substate-14.0.1.0.1.dev8.dist-info/RECORD
